<?xml version="1.0" encoding="UTF-8" standalone="no" ?>
<AttributeFile Mv="1" Sv="2">
	<PlatformSign>22359</PlatformSign>
	<RegisteredAttributes>
		<NumberOfRegisteredAttributes>16</NumberOfRegisteredAttributes>
		<Attributes Type="Städte">
			<RefID>1128879154</RefID>
		</Attributes>
		<Attributes Type="Mehrschichtige Bauteile">
			<RefID>1129791794</RefID>
		</Attributes>
		<Attributes Type="Bemaßungsstandards">
			<RefID>1398033970</RefID>
		</Attributes>
		<Attributes Type="Schraffurtypen">
			<RefID>1179208755</RefID>
		</Attributes>
		<Attributes Type="Ebenen">
			<RefID>1279351090</RefID>
		</Attributes>
		<Attributes Type="Ebenen-Kombinationen">
			<RefID>1279479602</RefID>
		</Attributes>
		<Attributes Type="Linientypen">
			<RefID>1279872562</RefID>
			<LineType Idx="1" Name="Zickzack 45°">
				<OdbObj Mv="3" Sv="0">
					<OdbRef>
						<guid>6A04CFB0-7EA8-45DC-8BBD-49122101280F</guid>
					</OdbRef>
					<CreaTime>4437</CreaTime>
					<ModiTime>4439</ModiTime>
				</OdbObj>
				<Name>Zickzack 45°</Name>
				<Index>1</Index>
				<Flags/>
				<ModiTime>0</ModiTime>
				<RegMemoTable MemoNumber="0" Mv="1" Sv="0"/>
				<ReadOnly>false</ReadOnly>
				<DefineScale>10</DefineScale>
				<LinePeriod>4</LinePeriod>
				<LineHeight>2</LineHeight>
				<LineType>SymbolLine</LineType>
				<LineFlags>FixScale</LineFlags>
				<LineItemsData Mv="1" Sv="0">
					<LineItem>
						<ItemType>CenterDotItemType</ItemType>
						<CenterDotItem>0</CenterDotItem>
					</LineItem>
					<LineItem>
						<ItemType>LineItemType</ItemType>
						<LineItemPosition>
							<X>0</X>
							<Y>0</Y>
						</LineItemPosition>
						<LineItemEndCoord>
							<X>1</X>
							<Y>0.999999999999999</Y>
						</LineItemEndCoord>
						<LineItemPosition>
							<X>1</X>
							<Y>0.999999999999999</Y>
						</LineItemPosition>
						<LineItemEndCoord>
							<X>3</X>
							<Y>-1</Y>
						</LineItemEndCoord>
						<LineItemPosition>
							<X>3</X>
							<Y>-1</Y>
						</LineItemPosition>
						<LineItemEndCoord>
							<X>4</X>
							<Y>0</Y>
						</LineItemEndCoord>
					</LineItem>
				</LineItemsData>
			</LineType>
			<LineType Idx="2" Name="Zickzack 60°">
				<OdbObj Mv="3" Sv="0">
					<OdbRef>
						<guid>591C51DF-79ED-4806-BAB4-7206BA2C0824</guid>
					</OdbRef>
					<CreaTime>4442</CreaTime>
					<ModiTime>4444</ModiTime>
				</OdbObj>
				<Name>Zickzack 60°</Name>
				<Index>2</Index>
				<Flags/>
				<ModiTime>0</ModiTime>
				<RegMemoTable MemoNumber="0" Mv="1" Sv="0"/>
				<ReadOnly>false</ReadOnly>
				<DefineScale>10</DefineScale>
				<LinePeriod>2.3</LinePeriod>
				<LineHeight>1.99185842870421</LineHeight>
				<LineType>SymbolLine</LineType>
				<LineFlags>FixScale</LineFlags>
				<LineItemsData Mv="1" Sv="0">
					<LineItem>
						<ItemType>LineItemType</ItemType>
						<LineItemPosition>
							<X>0.575</X>
							<Y>0.995929214352104</Y>
						</LineItemPosition>
						<LineItemEndCoord>
							<X>1.725</X>
							<Y>-0.995929214352105</Y>
						</LineItemEndCoord>
						<LineItemPosition>
							<X>0</X>
							<Y>0</Y>
						</LineItemPosition>
						<LineItemEndCoord>
							<X>0.575</X>
							<Y>0.995929214352104</Y>
						</LineItemEndCoord>
						<LineItemPosition>
							<X>1.725</X>
							<Y>-0.995929214352105</Y>
						</LineItemPosition>
						<LineItemEndCoord>
							<X>2.3</X>
							<Y>-2.15957723568467e-16</Y>
						</LineItemEndCoord>
					</LineItem>
				</LineItemsData>
			</LineType>
			<LineType Idx="3" Name="Zickzack 75°">
				<OdbObj Mv="3" Sv="0">
					<OdbRef>
						<guid>C677A25E-160D-4ECD-925A-515FABD5D7F1</guid>
					</OdbRef>
					<CreaTime>4447</CreaTime>
					<ModiTime>4449</ModiTime>
				</OdbObj>
				<Name>Zickzack 75°</Name>
				<Index>3</Index>
				<Flags/>
				<ModiTime>0</ModiTime>
				<RegMemoTable MemoNumber="0" Mv="1" Sv="0"/>
				<ReadOnly>false</ReadOnly>
				<DefineScale>10</DefineScale>
				<LinePeriod>1.1</LinePeriod>
				<LineHeight>2.05262794416289</LineHeight>
				<LineType>SymbolLine</LineType>
				<LineFlags>FixScale</LineFlags>
				<LineItemsData Mv="1" Sv="0">
					<LineItem>
						<ItemType>LineItemType</ItemType>
						<LineItemPosition>
							<X>0</X>
							<Y>0</Y>
						</LineItemPosition>
						<LineItemEndCoord>
							<X>0.275</X>
							<Y>1.02631397208144</Y>
						</LineItemEndCoord>
						<LineItemPosition>
							<X>0.275</X>
							<Y>1.02631397208144</Y>
						</LineItemPosition>
						<LineItemEndCoord>
							<X>0.825</X>
							<Y>-1.02631397208144</Y>
						</LineItemEndCoord>
						<LineItemPosition>
							<X>0.825</X>
							<Y>-1.02631397208144</Y>
						</LineItemPosition>
						<LineItemEndCoord>
							<X>1.1</X>
							<Y>-4.45092735273171e-16</Y>
						</LineItemEndCoord>
					</LineItem>
				</LineItemsData>
			</LineType>
			<LineType Idx="4" Name="Zickzack groß">
				<OdbObj Mv="3" Sv="0">
					<OdbRef>
						<guid>A1A19EBD-F57A-4631-BBB8-411ADED98458</guid>
					</OdbRef>
					<CreaTime>4452</CreaTime>
					<ModiTime>4454</ModiTime>
				</OdbObj>
				<Name>Zickzack groß</Name>
				<Index>4</Index>
				<Flags/>
				<ModiTime>0</ModiTime>
				<RegMemoTable MemoNumber="0" Mv="1" Sv="0"/>
				<ReadOnly>false</ReadOnly>
				<DefineScale>16</DefineScale>
				<LinePeriod>5.64444446563721</LinePeriod>
				<LineHeight>2.8222222328186</LineHeight>
				<LineType>SymbolLine</LineType>
				<LineFlags>FixScale</LineFlags>
				<LineItemsData Mv="1" Sv="0">
					<LineItem>
						<ItemType>LineItemType</ItemType>
						<LineItemPosition>
							<X>0</X>
							<Y>0</Y>
						</LineItemPosition>
						<LineItemEndCoord>
							<X>1.4111111164093</X>
							<Y>-1.4111111164093</Y>
						</LineItemEndCoord>
						<LineItemPosition>
							<X>1.4111111164093</X>
							<Y>-1.4111111164093</Y>
						</LineItemPosition>
						<LineItemEndCoord>
							<X>2.8222222328186</X>
							<Y>0</Y>
						</LineItemEndCoord>
						<LineItemPosition>
							<X>2.8222222328186</X>
							<Y>0</Y>
						</LineItemPosition>
						<LineItemEndCoord>
							<X>4.23333334922791</X>
							<Y>1.4111111164093</Y>
						</LineItemEndCoord>
						<LineItemPosition>
							<X>4.23333334922791</X>
							<Y>1.4111111164093</Y>
						</LineItemPosition>
						<LineItemEndCoord>
							<X>5.64444446563721</X>
							<Y>0</Y>
						</LineItemEndCoord>
					</LineItem>
				</LineItemsData>
			</LineType>
			<LineType Idx="5" Name="Zickzack Unterbrechung">
				<OdbObj Mv="3" Sv="0">
					<OdbRef>
						<guid>9FE15033-D97E-4B12-9FC8-3F64D59A10E0</guid>
					</OdbRef>
					<CreaTime>4457</CreaTime>
					<ModiTime>4459</ModiTime>
				</OdbObj>
				<Name>Zickzack Unterbrechung</Name>
				<Index>5</Index>
				<Flags/>
				<ModiTime>0</ModiTime>
				<RegMemoTable MemoNumber="0" Mv="1" Sv="0"/>
				<ReadOnly>false</ReadOnly>
				<DefineScale>10</DefineScale>
				<LinePeriod>6</LinePeriod>
				<LineHeight>2</LineHeight>
				<LineType>SymbolLine</LineType>
				<LineFlags>FixScale</LineFlags>
				<LineItemsData Mv="1" Sv="0">
					<LineItem>
						<ItemType>CenterDotItemType</ItemType>
						<CenterDotItem>0</CenterDotItem>
					</LineItem>
					<LineItem>
						<ItemType>CenterLineItemType</ItemType>
						<CenterLineBegin>1.07179676972449</CenterLineBegin>
						<CenterLineLength>4.92820323027551</CenterLineLength>
					</LineItem>
					<LineItem>
						<ItemType>LineItemType</ItemType>
						<LineItemPosition>
							<X>0</X>
							<Y>0</Y>
						</LineItemPosition>
						<LineItemEndCoord>
							<X>0.267949192431123</X>
							<Y>1</Y>
						</LineItemEndCoord>
						<LineItemPosition>
							<X>0.267949192431123</X>
							<Y>1</Y>
						</LineItemPosition>
						<LineItemEndCoord>
							<X>0.803847577293367</X>
							<Y>-1</Y>
						</LineItemEndCoord>
						<LineItemPosition>
							<X>0.803847577293367</X>
							<Y>-1</Y>
						</LineItemPosition>
						<LineItemEndCoord>
							<X>1.07179676972449</X>
							<Y>-4.33680868994202e-16</Y>
						</LineItemEndCoord>
					</LineItem>
				</LineItemsData>
			</LineType>
			<LineType Idx="6" Name="Welle 1">
				<OdbObj Mv="3" Sv="0">
					<OdbRef>
						<guid>ED27A90C-E5ED-4C68-B59C-FA60D56C45B1</guid>
					</OdbRef>
					<CreaTime>4462</CreaTime>
					<ModiTime>4464</ModiTime>
				</OdbObj>
				<Name>Welle 1</Name>
				<Index>6</Index>
				<Flags/>
				<ModiTime>0</ModiTime>
				<RegMemoTable MemoNumber="0" Mv="1" Sv="0"/>
				<ReadOnly>false</ReadOnly>
				<DefineScale>48</DefineScale>
				<LinePeriod>5.64444446563721</LinePeriod>
				<LineHeight>2.8222222328186</LineHeight>
				<LineType>SymbolLine</LineType>
				<LineFlags>FixScale</LineFlags>
				<LineItemsData Mv="1" Sv="0">
					<LineItem>
						<ItemType>ArcItemType</ItemType>
						<ArcItemPosition>
							<X>1.4111111164093</X>
							<Y>0</Y>
						</ArcItemPosition>
						<ArcItemRadius>1.4111111164093</ArcItemRadius>
						<ArcItemBeginAngle>3.14159265358979</ArcItemBeginAngle>
						<ArcItemEndAngle>6.28318530717959</ArcItemEndAngle>
						<ArcItemPosition>
							<X>4.23333334922791</X>
							<Y>0</Y>
						</ArcItemPosition>
						<ArcItemRadius>1.4111111164093</ArcItemRadius>
						<ArcItemBeginAngle>6.28318530717959</ArcItemBeginAngle>
						<ArcItemEndAngle>9.42477796076938</ArcItemEndAngle>
					</LineItem>
				</LineItemsData>
			</LineType>
			<LineType Idx="7" Name="Welle 2">
				<OdbObj Mv="3" Sv="0">
					<OdbRef>
						<guid>465A8B42-94AD-4EA9-BFA0-30498E346471</guid>
					</OdbRef>
					<CreaTime>4467</CreaTime>
					<ModiTime>4469</ModiTime>
				</OdbObj>
				<Name>Welle 2</Name>
				<Index>7</Index>
				<Flags/>
				<ModiTime>0</ModiTime>
				<RegMemoTable MemoNumber="0" Mv="1" Sv="0"/>
				<ReadOnly>false</ReadOnly>
				<DefineScale>1</DefineScale>
				<LinePeriod>4</LinePeriod>
				<LineHeight>1.15470053837925</LineHeight>
				<LineType>SymbolLine</LineType>
				<LineFlags>FixScale</LineFlags>
				<LineItemsData Mv="1" Sv="0">
					<LineItem>
						<ItemType>ArcItemType</ItemType>
						<ArcItemPosition>
							<X>1</X>
							<Y>-0.577350269189626</Y>
						</ArcItemPosition>
						<ArcItemRadius>1.15470053837925</ArcItemRadius>
						<ArcItemBeginAngle>0.523598775598299</ArcItemBeginAngle>
						<ArcItemEndAngle>2.61799387799149</ArcItemEndAngle>
						<ArcItemPosition>
							<X>3</X>
							<Y>0.577350269189627</Y>
						</ArcItemPosition>
						<ArcItemRadius>1.15470053837925</ArcItemRadius>
						<ArcItemBeginAngle>3.66519142918809</ArcItemBeginAngle>
						<ArcItemEndAngle>5.75958653158129</ArcItemEndAngle>
					</LineItem>
				</LineItemsData>
			</LineType>
			<LineType Idx="8" Name="Welle Sinus">
				<OdbObj Mv="3" Sv="0">
					<OdbRef>
						<guid>E6E8F802-BE69-409C-AE53-19CE638BC136</guid>
					</OdbRef>
					<CreaTime>4472</CreaTime>
					<ModiTime>4475</ModiTime>
				</OdbObj>
				<Name>Welle Sinus</Name>
				<Index>8</Index>
				<Flags/>
				<ModiTime>1540474378</ModiTime>
				<RegMemoTable MemoNumber="0" Mv="1" Sv="0"/>
				<ReadOnly>false</ReadOnly>
				<DefineScale>1</DefineScale>
				<LinePeriod>3</LinePeriod>
				<LineHeight>3</LineHeight>
				<LineType>SymbolLine</LineType>
				<LineFlags>FixScale</LineFlags>
				<LineItemsData Mv="1" Sv="0">
					<LineItem>
						<ItemType>LineItemType</ItemType>
						<LineItemPosition>
							<X>2.91666666666667</X>
							<Y>-0.260472266500396</Y>
						</LineItemPosition>
						<LineItemEndCoord>
							<X>3</X>
							<Y>-3.33066907387547e-16</Y>
						</LineItemEndCoord>
						<LineItemPosition>
							<X>0</X>
							<Y>0</Y>
						</LineItemPosition>
						<LineItemEndCoord>
							<X>0.0833333333333333</X>
							<Y>0.260472266500395</Y>
						</LineItemEndCoord>
						<LineItemPosition>
							<X>0.0833333333333333</X>
							<Y>0.260472266500395</Y>
						</LineItemPosition>
						<LineItemEndCoord>
							<X>0.166666666666667</X>
							<Y>0.513030214988502</Y>
						</LineItemEndCoord>
						<LineItemPosition>
							<X>0.166666666666667</X>
							<Y>0.513030214988502</Y>
						</LineItemPosition>
						<LineItemEndCoord>
							<X>0.25</X>
							<Y>0.75</Y>
						</LineItemEndCoord>
						<LineItemPosition>
							<X>0.25</X>
							<Y>0.75</Y>
						</LineItemPosition>
						<LineItemEndCoord>
							<X>0.333333333333333</X>
							<Y>0.96418141452981</Y>
						</LineItemEndCoord>
						<LineItemPosition>
							<X>0.333333333333333</X>
							<Y>0.96418141452981</Y>
						</LineItemPosition>
						<LineItemEndCoord>
							<X>0.416666666666666</X>
							<Y>1.14906666467847</Y>
						</LineItemEndCoord>
						<LineItemPosition>
							<X>0.416666666666666</X>
							<Y>1.14906666467847</Y>
						</LineItemPosition>
						<LineItemEndCoord>
							<X>0.5</X>
							<Y>1.29903810567666</Y>
						</LineItemEndCoord>
						<LineItemPosition>
							<X>0.5</X>
							<Y>1.29903810567666</Y>
						</LineItemPosition>
						<LineItemEndCoord>
							<X>0.583333333333333</X>
							<Y>1.40953893117886</Y>
						</LineItemEndCoord>
						<LineItemPosition>
							<X>0.583333333333333</X>
							<Y>1.40953893117886</Y>
						</LineItemPosition>
						<LineItemEndCoord>
							<X>0.666666666666667</X>
							<Y>1.47721162951831</Y>
						</LineItemEndCoord>
						<LineItemPosition>
							<X>0.666666666666667</X>
							<Y>1.47721162951831</Y>
						</LineItemPosition>
						<LineItemEndCoord>
							<X>0.75</X>
							<Y>1.5</Y>
						</LineItemEndCoord>
						<LineItemPosition>
							<X>0.75</X>
							<Y>1.5</Y>
						</LineItemPosition>
						<LineItemEndCoord>
							<X>0.833333333333332</X>
							<Y>1.47721162951831</Y>
						</LineItemEndCoord>
						<LineItemPosition>
							<X>0.833333333333332</X>
							<Y>1.47721162951831</Y>
						</LineItemPosition>
						<LineItemEndCoord>
							<X>0.916666666666666</X>
							<Y>1.40953893117886</Y>
						</LineItemEndCoord>
						<LineItemPosition>
							<X>0.916666666666666</X>
							<Y>1.40953893117886</Y>
						</LineItemPosition>
						<LineItemEndCoord>
							<X>0.999999999999999</X>
							<Y>1.29903810567666</Y>
						</LineItemEndCoord>
						<LineItemPosition>
							<X>0.999999999999999</X>
							<Y>1.29903810567666</Y>
						</LineItemPosition>
						<LineItemEndCoord>
							<X>1.08333333333333</X>
							<Y>1.14906666467847</Y>
						</LineItemEndCoord>
						<LineItemPosition>
							<X>1.08333333333333</X>
							<Y>1.14906666467847</Y>
						</LineItemPosition>
						<LineItemEndCoord>
							<X>1.16666666666666</X>
							<Y>0.96418141452981</Y>
						</LineItemEndCoord>
						<LineItemPosition>
							<X>1.16666666666666</X>
							<Y>0.96418141452981</Y>
						</LineItemPosition>
						<LineItemEndCoord>
							<X>1.25</X>
							<Y>0.75</Y>
						</LineItemEndCoord>
						<LineItemPosition>
							<X>1.25</X>
							<Y>0.75</Y>
						</LineItemPosition>
						<LineItemEndCoord>
							<X>1.33333333333333</X>
							<Y>0.513030214988502</Y>
						</LineItemEndCoord>
						<LineItemPosition>
							<X>1.33333333333333</X>
							<Y>0.513030214988502</Y>
						</LineItemPosition>
						<LineItemEndCoord>
							<X>1.41666666666667</X>
							<Y>0.260472266500395</Y>
						</LineItemEndCoord>
						<LineItemPosition>
							<X>1.41666666666667</X>
							<Y>0.260472266500395</Y>
						</LineItemPosition>
						<LineItemEndCoord>
							<X>1.5</X>
							<Y>3.33066907387547e-16</Y>
						</LineItemEndCoord>
						<LineItemPosition>
							<X>1.5</X>
							<Y>3.33066907387547e-16</Y>
						</LineItemPosition>
						<LineItemEndCoord>
							<X>1.58333333333333</X>
							<Y>-0.260472266500396</Y>
						</LineItemEndCoord>
						<LineItemPosition>
							<X>1.58333333333333</X>
							<Y>-0.260472266500396</Y>
						</LineItemPosition>
						<LineItemEndCoord>
							<X>1.66666666666666</X>
							<Y>-0.513030214988502</Y>
						</LineItemEndCoord>
						<LineItemPosition>
							<X>1.66666666666666</X>
							<Y>-0.513030214988502</Y>
						</LineItemPosition>
						<LineItemEndCoord>
							<X>1.75</X>
							<Y>-0.75</Y>
						</LineItemEndCoord>
						<LineItemPosition>
							<X>1.75</X>
							<Y>-0.75</Y>
						</LineItemPosition>
						<LineItemEndCoord>
							<X>1.83333333333333</X>
							<Y>-0.96418141452981</Y>
						</LineItemEndCoord>
						<LineItemPosition>
							<X>1.83333333333333</X>
							<Y>-0.96418141452981</Y>
						</LineItemPosition>
						<LineItemEndCoord>
							<X>1.91666666666667</X>
							<Y>-1.14906666467847</Y>
						</LineItemEndCoord>
						<LineItemPosition>
							<X>1.91666666666667</X>
							<Y>-1.14906666467847</Y>
						</LineItemPosition>
						<LineItemEndCoord>
							<X>2</X>
							<Y>-1.29903810567666</Y>
						</LineItemEndCoord>
						<LineItemPosition>
							<X>2</X>
							<Y>-1.29903810567666</Y>
						</LineItemPosition>
						<LineItemEndCoord>
							<X>2.08333333333333</X>
							<Y>-1.40953893117886</Y>
						</LineItemEndCoord>
						<LineItemPosition>
							<X>2.08333333333333</X>
							<Y>-1.40953893117886</Y>
						</LineItemPosition>
						<LineItemEndCoord>
							<X>2.16666666666667</X>
							<Y>-1.47721162951831</Y>
						</LineItemEndCoord>
						<LineItemPosition>
							<X>2.16666666666667</X>
							<Y>-1.47721162951831</Y>
						</LineItemPosition>
						<LineItemEndCoord>
							<X>2.25</X>
							<Y>-1.5</Y>
						</LineItemEndCoord>
						<LineItemPosition>
							<X>2.25</X>
							<Y>-1.5</Y>
						</LineItemPosition>
						<LineItemEndCoord>
							<X>2.33333333333333</X>
							<Y>-1.47721162951831</Y>
						</LineItemEndCoord>
						<LineItemPosition>
							<X>2.33333333333333</X>
							<Y>-1.47721162951831</Y>
						</LineItemPosition>
						<LineItemEndCoord>
							<X>2.41666666666666</X>
							<Y>-1.40953893117886</Y>
						</LineItemEndCoord>
						<LineItemPosition>
							<X>2.41666666666666</X>
							<Y>-1.40953893117886</Y>
						</LineItemPosition>
						<LineItemEndCoord>
							<X>2.5</X>
							<Y>-1.29903810567666</Y>
						</LineItemEndCoord>
						<LineItemPosition>
							<X>2.5</X>
							<Y>-1.29903810567666</Y>
						</LineItemPosition>
						<LineItemEndCoord>
							<X>2.58333333333333</X>
							<Y>-1.14906666467847</Y>
						</LineItemEndCoord>
						<LineItemPosition>
							<X>2.58333333333333</X>
							<Y>-1.14906666467847</Y>
						</LineItemPosition>
						<LineItemEndCoord>
							<X>2.66666666666667</X>
							<Y>-0.96418141452981</Y>
						</LineItemEndCoord>
						<LineItemPosition>
							<X>2.66666666666667</X>
							<Y>-0.96418141452981</Y>
						</LineItemPosition>
						<LineItemEndCoord>
							<X>2.75</X>
							<Y>-0.750000000000001</Y>
						</LineItemEndCoord>
						<LineItemPosition>
							<X>2.75</X>
							<Y>-0.750000000000001</Y>
						</LineItemPosition>
						<LineItemEndCoord>
							<X>2.83333333333333</X>
							<Y>-0.513030214988502</Y>
						</LineItemEndCoord>
						<LineItemPosition>
							<X>2.83333333333333</X>
							<Y>-0.513030214988502</Y>
						</LineItemPosition>
						<LineItemEndCoord>
							<X>2.91666666666667</X>
							<Y>-0.260472266500396</Y>
						</LineItemEndCoord>
					</LineItem>
				</LineItemsData>
			</LineType>
			<LineType Idx="9" Name="Blase">
				<OdbObj Mv="3" Sv="0">
					<OdbRef>
						<guid>EFF06D3C-207A-4E8C-8BD5-5ACF3100B06A</guid>
					</OdbRef>
					<CreaTime>4478</CreaTime>
					<ModiTime>4480</ModiTime>
				</OdbObj>
				<Name>Blase</Name>
				<Index>9</Index>
				<Flags/>
				<ModiTime>0</ModiTime>
				<RegMemoTable MemoNumber="0" Mv="1" Sv="0"/>
				<ReadOnly>false</ReadOnly>
				<DefineScale>100</DefineScale>
				<LinePeriod>39.67</LinePeriod>
				<LineHeight>10.5199387837302</LineHeight>
				<LineType>SymbolLine</LineType>
				<LineFlags>FixScale</LineFlags>
				<LineItemsData Mv="1" Sv="0">
					<LineItem>
						<ItemType>ArcItemType</ItemType>
						<ArcItemPosition>
							<X>5.49168441491964</X>
							<Y>0.236818840958144</Y>
						</ArcItemPosition>
						<ArcItemRadius>5.49678823282324</ArcItemRadius>
						<ArcItemBeginAngle>-3.09849618446868</ArcItemBeginAngle>
						<ArcItemEndAngle>-0.0430964691211169</ArcItemEndAngle>
						<ArcItemPosition>
							<X>15.3487257470377</X>
							<Y>0.886155254985085</Y>
						</ArcItemPosition>
						<ArcItemRadius>4.45439245582035</ArcItemRadius>
						<ArcItemBeginAngle>-2.94131683353226</ArcItemBeginAngle>
						<ArcItemEndAngle>-0.200275820057536</ArcItemEndAngle>
						<ArcItemPosition>
							<X>24.7921509148545</X>
							<Y>1.81157744410076</Y>
						</ArcItemPosition>
						<ArcItemRadius>5.39152946703572</ArcItemRadius>
						<ArcItemBeginAngle>-2.79892126135884</ArcItemBeginAngle>
						<ArcItemEndAngle>-0.342671392230951</ArcItemEndAngle>
						<ArcItemPosition>
							<X>34.7701095827365</X>
							<Y>1.35515474608233</Y>
						</ArcItemPosition>
						<ArcItemRadius>5.08383423087535</ArcItemRadius>
						<ArcItemBeginAngle>-2.87176891942227</ArcItemBeginAngle>
						<ArcItemEndAngle>-0.269823734167519</ArcItemEndAngle>
					</LineItem>
				</LineItemsData>
			</LineType>
		</Attributes>
		<Attributes Type="Oberflächen">
			<RefID>1296127026</RefID>
		</Attributes>
		<Attributes Type="Stifte">
			<RefID>1347699276</RefID>
		</Attributes>
		<Attributes Type="Raumkategorien">
			<RefID>1380795186</RefID>
		</Attributes>
		<Attributes Type="Projektmarker-Stile">
			<RefID>1297306713</RefID>
		</Attributes>
		<Attributes Type="Profile">
			<RefID>1347571526</RefID>
		</Attributes>
		<Attributes Type="HKLSE/MEP-Systeme">
			<RefID>1296388179</RefID>
		</Attributes>
		<Attributes Type="Nutzungsprofile">
			<RefID>1162104656</RefID>
		</Attributes>
		<Attributes Type="Umbau-Überschreibungsstile">
			<RefID>1196381778</RefID>
		</Attributes>
		<Attributes Type="Baustoffe">
			<RefID>1112359252</RefID>
		</Attributes>
	</RegisteredAttributes>
</AttributeFile>
